{
  "$schema": "https://ui.shadcn.com/schema/registry-item.json",
  "name": "cards",
  "type": "registry:component",
  "title": "Cards",
  "description": "A card component with animations.",
  "dependencies": [
    "motion",
    "lucide-react"
  ],
  "files": [
    {
      "path": "src/registry/default/cards.tsx",
      "content": "\"use client\";\nimport { useState } from \"react\";\nimport { motion, AnimatePresence } from \"motion/react\";\nimport { X } from \"lucide-react\";\n\ntype Card = {\n  id: string;\n  title: string;\n  category: string;\n  description: string;\n  content: string;\n};\n\nconst cards: Card[] = [\n  {\n    id: \"card-1\",\n    category: \"Core Feature\",\n    title: \"Dynamic Content Rendering\",\n    description:\n      \"Leverage server-side capabilities for blazing-fast page loads and optimal SEO performance.\",\n    content:\n      \"Our architecture allows for rendering content dynamically on the server based on user requests. This ensures that the initial HTML sent to the browser is fully populated, which is crucial for search engine crawlers and provides a near-instantaneous first paint for users. It also reduces the amount of JavaScript needed on the client-side, further boosting performance.\",\n  },\n  {\n    id: \"card-2\",\n    category: \"API Integration\",\n    title: \"Seamless API Connectivity\",\n    description:\n      \"Integrate with any third-party service using our robust and flexible API gateway.\",\n    content:\n      \"The API gateway is designed for high availability and low latency. It supports REST, GraphQL, and gRPC protocols out-of-the-box. Built-in authentication, rate limiting, and caching layers protect your backend services and ensure a smooth experience for developers and end-users. Detailed logging and monitoring provide full visibility into your API traffic.\",\n  },\n  {\n    id: \"card-3\",\n    category: \"Performance\",\n    title: \"Global Edge Network\",\n    description:\n      \"Serve content from the edge, closer to your users, for unparalleled speed and reliability.\",\n    content:\n      \"By deploying your static assets and serverless functions to our global edge network, you can significantly reduce latency. User requests are automatically routed to the nearest data center. This not only improves speed but also enhances reliability by distributing traffic and providing resilience against regional outages. The network includes powerful caching and DDoS protection.\",\n  },\n];\n\nexport default function Cards() {\n  const [selectedCard, setSelectedCard] = useState<Card | null>(null);\n\n  return (\n    <div className=\"relative flex min-h-screen w-full items-center justify-center p-4 font-sans\">\n      {/* Main cards list */}\n      <div className=\"grid w-full max-w-4xl grid-cols-1 gap-6 md:grid-cols-3\">\n        {cards.map((card) => (\n          <motion.div\n            key={card.id}\n            layoutId={card.id}\n            onClick={() => setSelectedCard(card)}\n            className=\"bg-light 700 relative cursor-pointer rounded-lg p-6 shadow-xl transition-shadow duration-300 hover:shadow-2xl hover:shadow-neutral-600\"\n          >\n            <h2 className=\"mb-1 text-xl font-semibold text-neutral-100\">\n              {card.title}\n            </h2>\n            <p className=\"text-neutral-400\">{card.description}</p>\n          </motion.div>\n        ))}\n      </div>\n\n      <AnimatePresence>\n        {selectedCard && (\n          <div className=\"absolute inset-0 z-50 flex items-center justify-center p-4\">\n            {/* Backdrop */}\n            <motion.div\n              initial={{ opacity: 0 }}\n              animate={{ opacity: 1 }}\n              exit={{ opacity: 0 }}\n              onClick={() => setSelectedCard(null)}\n              className=\"absolute inset-0 bg-black/50 backdrop-blur-sm\"\n            />\n\n            {/* Expanded Card */}\n            <motion.div\n              transition={{ duration: 0.2, ease: \"easeInOut\" }}\n              layoutId={selectedCard.id}\n              className=\"bg-light relative z-10 max-w-sm rounded-lg p-8 shadow-2xl\"\n            >\n              <motion.button\n                onClick={() => setSelectedCard(null)}\n                className=\"absolute top-4 right-4 text-neutral-500 hover:text-neutral-200\"\n                aria-label=\"Close\"\n              >\n                <X size={24} />\n              </motion.button>\n\n              <motion.div\n                initial={{ opacity: 0 }}\n                animate={{ opacity: 1 }}\n                exit={{ opacity: 0 }}\n              >\n                <div className=\"mb-6 flex items-center space-x-4\">\n                  <div>\n                    <p className=\"text-sm text-neutral-400\">\n                      {selectedCard.category}\n                    </p>\n                    <h2 className=\"text-3xl font-bold text-neutral-100\">\n                      {selectedCard.title}\n                    </h2>\n                  </div>\n                </div>\n                <div className=\"prose prose-invert max-w-none text-neutral-300\">\n                  {selectedCard.content}\n                </div>\n              </motion.div>\n            </motion.div>\n          </div>\n        )}\n      </AnimatePresence>\n    </div>\n  );\n}\n",
      "type": "registry:component"
    }
  ]
}